saltext/heist/__init__.py
saltext/heist/loader.py
saltext/heist/version.py
saltext/heist/runners/__init__.py
saltext/heist/runners/heist.py
saltext/heist/runners/heist_salt.py
saltext.heist-1.0.0b0.dist-info/LICENSE
saltext.heist-1.0.0b0.dist-info/METADATA
saltext.heist-1.0.0b0.dist-info/NOTICE
saltext.heist-1.0.0b0.dist-info/WHEEL
saltext.heist-1.0.0b0.dist-info/entry_points.txt
saltext.heist-1.0.0b0.dist-info/top_level.txt
saltext.heist-1.0.0b0.dist-info/RECORD
