Metadata-Version: 2.1
Name: saltext.heist
Version: 1.0.0b0
Summary: Salt Extension for Heist and Heist Salt
Home-page: https://gitlab.com/saltstack/pop/heist
Author: Megan Wilhite
Author-email: megan.wilhite@gmail.com
License: Apache Software License
Project-URL: Source, https://gitlab.com/saltstack/pop/heist
Project-URL: Tracker, https://gitlab.com/saltstack/pop/heist/issues
Keywords: salt-extension
Platform: any
Classifier: Programming Language :: Python
Classifier: Programming Language :: Cython
Classifier: Programming Language :: Python :: 3
Classifier: Programming Language :: Python :: 3 :: Only
Classifier: Programming Language :: Python :: 3.5
Classifier: Programming Language :: Python :: 3.6
Classifier: Programming Language :: Python :: 3.7
Classifier: Programming Language :: Python :: 3.8
Classifier: Programming Language :: Python :: 3.9
Classifier: Development Status :: 4 - Beta
Classifier: Intended Audience :: Developers
Classifier: License :: OSI Approved :: Apache Software License
Requires-Python: >=3.5
